gdrive/__init__.py
gdrive/__main__.py
gdrive/api.py
gdrive/cli.py
gdrive/commands/__init__.py
gdrive/commands/about.py
gdrive/commands/download.py
gdrive/commands/files.py
gdrive/commands/folders.py
gdrive/commands/list.py
gdrive/commands/rename.py
gdrive/commands/renamelist.py
gdrive/commands/uploaddir.py
gdrive/commands/uploadfile.py
gdrive/commands/uploadlist.py
rlane_gdrive-1.0.5.dist-info/METADATA
rlane_gdrive-1.0.5.dist-info/WHEEL
rlane_gdrive-1.0.5.dist-info/entry_points.txt
rlane_gdrive-1.0.5.dist-info/licenses/LICENSE
rlane_gdrive-1.0.5.dist-info/RECORD
