Metadata-Version: 2.1
Name: rlane-gdrive
Version: 1.0.5
Summary: Google Drive CLI
Keywords: google,drive,gdrive
Author-Email: Russel Lane <russel@rlane.com>
License: MIT
Classifier: Development Status :: 4 - Beta
Classifier: Intended Audience :: End Users/Desktop
Classifier: License :: OSI Approved :: MIT License
Classifier: Programming Language :: Python :: 3
Project-URL: Homepage, https://github.com/russellane/gdrive
Requires-Python: >=3.10
Requires-Dist: loguru>=0.7.3
Requires-Dist: python-magic>=0.4.27
Requires-Dist: rich>=13.9.4
Requires-Dist: rlane-libcli>=1.0.8
Requires-Dist: rlane-libfile>=1.0.2
Requires-Dist: rlane-libgoogle>=1.0.2
